setup.py
distributions_Rohit/Binomialdistribution.py
distributions_Rohit/Gaussiandistribution.py
distributions_Rohit/Generaldistribution.py
distributions_Rohit/__init__.py
distributions_Rohit.egg-info/PKG-INFO
distributions_Rohit.egg-info/SOURCES.txt
distributions_Rohit.egg-info/dependency_links.txt
distributions_Rohit.egg-info/not-zip-safe
distributions_Rohit.egg-info/top_level.txt